fyg/__init__.py
fyg/config.py
fyg/membank.py
fyg/pcache.py
fyg/util/__init__.py
fyg/util/io.py
fyg/util/reporting.py
fyg-0.1.7.9.dist-info/LICENSE
fyg-0.1.7.9.dist-info/METADATA
fyg-0.1.7.9.dist-info/WHEEL
fyg-0.1.7.9.dist-info/top_level.txt
fyg-0.1.7.9.dist-info/RECORD
