Metadata-Version: 2.1
Name: fyg
Version: 0.1.7.9
Summary: FancY confiG
Author: Mario Balibrera
Author-email: mario.balibrera@gmail.com
License: MIT License
Classifier: Development Status :: 3 - Alpha
Classifier: Environment :: Console
Classifier: Intended Audience :: Developers
Classifier: License :: OSI Approved :: MIT License
Classifier: Operating System :: OS Independent
Classifier: Programming Language :: Python
Classifier: Topic :: Software Development :: Libraries :: Python Modules
License-File: LICENSE
Requires-Dist: python-dotenv >=1.1.1
